fs_box_sync/__init__.py
fs_box_sync/box.py
fs_box_sync/box_api.py
fs_box_sync/box_drive.py
fs_box_sync/box_fs.py
fs_box_sync/exceptions.py
fs_box_sync/py.typed
fs_box_sync/types.py
fs_box_sync/utils.py
fs_box_sync-0.1.0.dist-info/METADATA
fs_box_sync-0.1.0.dist-info/WHEEL
fs_box_sync-0.1.0.dist-info/RECORD
