Metadata-Version: 2.4
Name: fs-box-sync
Version: 0.1.0
Summary: Python SDK for Box API with seamless Box Drive integration
Requires-Python: >=3.12
Requires-Dist: aiofiles>=24.0.0
Requires-Dist: httpx>=0.27.0
Requires-Dist: platformdirs>=4.0.0
Requires-Dist: pydantic>=2.0.0
Provides-Extra: dev
Requires-Dist: pyright>=1.1.0; extra == 'dev'
Requires-Dist: pytest-asyncio>=0.23.0; extra == 'dev'
Requires-Dist: pytest-cov>=4.1.0; extra == 'dev'
Requires-Dist: pytest>=8.0.0; extra == 'dev'
Requires-Dist: respx>=0.20.0; extra == 'dev'
Requires-Dist: ruff>=0.2.0; extra == 'dev'
